<annotation>
	<folder>還沒放上去</folder>
	<filename>84.JPG</filename>
	<path>C:\Ying-Ju Chen\Lab\robot xarm\GitHub\curebot\images\還沒放上去\84.JPG</path>
	<source>
		<database>Unknown</database>
	</source>
	<size>
		<width>4000</width>
		<height>3000</height>
		<depth>3</depth>
	</size>
	<segmented>0</segmented>
	<object>
		<name>wound</name>
		<pose>Unspecified</pose>
		<truncated>0</truncated>
		<difficult>0</difficult>
		<bndbox>
			<xmin>1275</xmin>
			<ymin>919</ymin>
			<xmax>2694</xmax>
			<ymax>1930</ymax>
		</bndbox>
	</object>
</annotation>
